darca_log_facility/__init__.py
darca_log_facility/__version__.py
darca_log_facility/logger.py
darca_log_facility-0.1.0.dist-info/LICENSE
darca_log_facility-0.1.0.dist-info/METADATA
darca_log_facility-0.1.0.dist-info/WHEEL
darca_log_facility-0.1.0.dist-info/RECORD
