Metadata-Version: 2.3
Name: darca-log-facility
Version: 0.1.0
Summary: Logging facility for reuse along projects.
License: LICENSE
Author: Roel Kist
Author-email: roel.kist@gmail.com
Requires-Python: >=3.12,<4.0
Classifier: License :: Other/Proprietary License
Classifier: Programming Language :: Python :: 3
Classifier: Programming Language :: Python :: 3.12
Classifier: Programming Language :: Python :: 3.13
Requires-Dist: colorlog (>=6.9.0,<7.0.0)
